topspy/__init__.py
topspy/version.py
topspy/AutoModeler/BuildingFrame3D.py
topspy/AutoModeler/ElasticSDF.py
topspy/AutoModeler/NSDF.py
topspy/AutoModeler/__init__.py
topspy/dynamic/FFT.py
topspy/dynamic/KMCMatrixes.py
topspy/dynamic/LAT2.py
topspy/dynamic/RspSpc.py
topspy/dynamic/SDFTHA.py
topspy/dynamic/__init__.py
topspy/modeling/ElePerPend.py
topspy/modeling/GmTVector.py
topspy/modeling/MultiEl.py
topspy/modeling/__init__.py
topspy/modeling/eleAxialForce.py
topspy/timehistories/__init__.py
topspy/timehistories/FarFieldFemaP695/1.AT2
topspy/timehistories/FarFieldFemaP695/10.AT2
topspy/timehistories/FarFieldFemaP695/11.AT2
topspy/timehistories/FarFieldFemaP695/12.AT2
topspy/timehistories/FarFieldFemaP695/13.AT2
topspy/timehistories/FarFieldFemaP695/14.AT2
topspy/timehistories/FarFieldFemaP695/15.AT2
topspy/timehistories/FarFieldFemaP695/16.AT2
topspy/timehistories/FarFieldFemaP695/17.AT2
topspy/timehistories/FarFieldFemaP695/18.AT2
topspy/timehistories/FarFieldFemaP695/19.AT2
topspy/timehistories/FarFieldFemaP695/2.AT2
topspy/timehistories/FarFieldFemaP695/20.AT2
topspy/timehistories/FarFieldFemaP695/21.AT2
topspy/timehistories/FarFieldFemaP695/22.AT2
topspy/timehistories/FarFieldFemaP695/23.AT2
topspy/timehistories/FarFieldFemaP695/24.AT2
topspy/timehistories/FarFieldFemaP695/25.AT2
topspy/timehistories/FarFieldFemaP695/26.AT2
topspy/timehistories/FarFieldFemaP695/27.AT2
topspy/timehistories/FarFieldFemaP695/28.AT2
topspy/timehistories/FarFieldFemaP695/29.AT2
topspy/timehistories/FarFieldFemaP695/3.AT2
topspy/timehistories/FarFieldFemaP695/30.AT2
topspy/timehistories/FarFieldFemaP695/31.AT2
topspy/timehistories/FarFieldFemaP695/32.AT2
topspy/timehistories/FarFieldFemaP695/33.AT2
topspy/timehistories/FarFieldFemaP695/34.AT2
topspy/timehistories/FarFieldFemaP695/35.AT2
topspy/timehistories/FarFieldFemaP695/36.AT2
topspy/timehistories/FarFieldFemaP695/37.AT2
topspy/timehistories/FarFieldFemaP695/38.AT2
topspy/timehistories/FarFieldFemaP695/39.AT2
TOpsPy-0.0.31.dist-info/LICENSE
TOpsPy-0.0.31.dist-info/METADATA
TOpsPy-0.0.31.dist-info/WHEEL
TOpsPy-0.0.31.dist-info/top_level.txt
TOpsPy-0.0.31.dist-info/RECORD
