Metadata-Version: 2.1
Name: TOpsPy
Version: 0.0.31
Summary: OpenseesPy Functions
Home-page: https://github.com/BijanSeif
Author: BijanSeif (Bijan Sayyafzadeh)
Author-email: <b.sayyaf@yahoo.com>
Keywords: python,opensees,Modeling,Dynamic
Classifier: Programming Language :: Python :: 3.8
Classifier: Topic :: Software Development :: Libraries :: Python Modules
Classifier: Operating System :: Microsoft :: Windows
License-File: LICENSE
Requires-Dist: openseespy
Requires-Dist: eseesminipy
Requires-Dist: numpy
